nat/meta/pypi.md
nat/plugins/data_flywheel/observability/__init__.py
nat/plugins/data_flywheel/observability/register.py
nat/plugins/data_flywheel/observability/exporter/__init__.py
nat/plugins/data_flywheel/observability/exporter/dfw_elasticsearch_exporter.py
nat/plugins/data_flywheel/observability/exporter/dfw_exporter.py
nat/plugins/data_flywheel/observability/mixin/__init__.py
nat/plugins/data_flywheel/observability/mixin/elasticsearch_mixin.py
nat/plugins/data_flywheel/observability/processor/__init__.py
nat/plugins/data_flywheel/observability/processor/dfw_record_processor.py
nat/plugins/data_flywheel/observability/processor/trace_conversion/__init__.py
nat/plugins/data_flywheel/observability/processor/trace_conversion/span_extractor.py
nat/plugins/data_flywheel/observability/processor/trace_conversion/span_to_dfw.py
nat/plugins/data_flywheel/observability/processor/trace_conversion/trace_adapter_registry.py
nat/plugins/data_flywheel/observability/processor/trace_conversion/adapter/__init__.py
nat/plugins/data_flywheel/observability/processor/trace_conversion/adapter/register.py
nat/plugins/data_flywheel/observability/processor/trace_conversion/adapter/elasticsearch/__init__.py
nat/plugins/data_flywheel/observability/processor/trace_conversion/adapter/elasticsearch/nim_converter.py
nat/plugins/data_flywheel/observability/processor/trace_conversion/adapter/elasticsearch/openai_converter.py
nat/plugins/data_flywheel/observability/schema/__init__.py
nat/plugins/data_flywheel/observability/schema/register.py
nat/plugins/data_flywheel/observability/schema/schema_registry.py
nat/plugins/data_flywheel/observability/schema/trace_container.py
nat/plugins/data_flywheel/observability/schema/trace_source_base.py
nat/plugins/data_flywheel/observability/schema/provider/__init__.py
nat/plugins/data_flywheel/observability/schema/provider/nim_trace_source.py
nat/plugins/data_flywheel/observability/schema/provider/openai_message.py
nvidia_nat_data_flywheel-1.3.1.dist-info/licenses/LICENSE-3rd-party.txt
nvidia_nat_data_flywheel-1.3.1.dist-info/licenses/LICENSE.md
nvidia_nat_data_flywheel-1.3.1.dist-info/METADATA
nvidia_nat_data_flywheel-1.3.1.dist-info/WHEEL
nvidia_nat_data_flywheel-1.3.1.dist-info/entry_points.txt
nvidia_nat_data_flywheel-1.3.1.dist-info/top_level.txt
nvidia_nat_data_flywheel-1.3.1.dist-info/RECORD
