Metadata-Version: 2.4
Name: nvidia-nat-data-flywheel
Version: 1.3.1
Summary: Subpackage for NVIDIA Data Flywheel Blueprint integration in NeMo Agent Toolkit
Author: NVIDIA Corporation
Maintainer: NVIDIA Corporation
License: Apache-2.0
Project-URL: documentation, https://docs.nvidia.com/nemo/agent-toolkit/latest/
Project-URL: source, https://github.com/NVIDIA/NeMo-Agent-Toolkit
Keywords: ai,observability,nemo,data flywheel
Classifier: Programming Language :: Python
Classifier: Programming Language :: Python :: 3.11
Classifier: Programming Language :: Python :: 3.12
Classifier: Programming Language :: Python :: 3.13
Requires-Python: <3.14,>=3.11
License-File: LICENSE-3rd-party.txt
License-File: LICENSE.md
Requires-Dist: elasticsearch~=8.1
Requires-Dist: nvidia-nat==v1.3.1
Dynamic: license-file
